{"schema":{"Cluster":{"id":"Cluster","type":{"dataType":"reference","referenceType":"VC:ClusterComputeResource"},"label":"Cluster","constraints":{"required":false},"valueList":{"type":"scriptAction","id":"com.vmware.library.vc.cluster/getAllClusterComputeResourceForVimHost","parameters":[{"vimHost":"vimHost","$type":{"dataType":"reference","referenceType":"VC:SdkConnection"}}]}},"parrent_rp":{"id":"parrent_rp","type":{"dataType":"reference","referenceType":"VC:ResourcePool"},"label":"parrent_rp","constraints":{"required":false},"valueList":{"type":"scriptAction","id":"uno.vixen.vm/Get_RP_in_Cluster","parameters":[{"Cluster":"Cluster","$type":{"dataType":"reference","referenceType":"VC:ClusterComputeResource"}}]}},"Name":{"id":"Name","type":{"dataType":"string"},"label":"Name","constraints":{"required":false}}},"layout":{"pages":[{"id":"page_ra97sct0","sections":[{"id":"section_a98484ad","fields":[{"id":"Cluster","display":"valuePicker","signpostPosition":"right-middle","state":{"visible":true,"read-only":false}}]},{"id":"section_ho4gaat3","fields":[{"id":"parrent_rp","display":"valuePicker","signpostPosition":"right-middle","state":{"visible":true,"read-only":false}}]},{"id":"section_0b0g1xib","fields":[{"id":"Name","display":"textField","signpostPosition":"right-middle","state":{"visible":true,"read-only":false}}]}],"title":"General"}]},"options":{"externalValidations":[]},"itemId":""}